{"trial_id": "0021", "hyperparameters": {"space": [{"class_name": "Int", "config": {"name": "units", "default": null, "conditions": [], "min_value": 32, "max_value": 512, "step": 32, "sampling": "linear"}}, {"class_name": "Float", "config": {"name": "dropout", "default": 0.0, "conditions": [], "min_value": 0.0, "max_value": 0.5, "step": 0.1, "sampling": "linear"}}, {"class_name": "Float", "config": {"name": "learning_rate", "default": 0.0001, "conditions": [], "min_value": 0.0001, "max_value": 0.01, "step": null, "sampling": "log"}}], "values": {"units": 448, "dropout": 0.0, "learning_rate": 0.0002913500886838151, "tuner/epochs": 4, "tuner/initial_epoch": 0, "tuner/bracket": 1, "tuner/round": 0}}, "metrics": {"metrics": {"loss": {"direction": "min", "observations": [{"value": [204.33529663085938], "step": 0}]}, "accuracy": {"direction": "max", "observations": [{"value": [0.49602824449539185], "step": 0}]}, "val_loss": {"direction": "min", "observations": [{"value": [25.551847457885742], "step": 0}]}, "val_accuracy": {"direction": "max", "observations": [{"value": [0.5502645373344421], "step": 0}]}}}, "score": 0.5502645373344421, "best_step": 0, "status": "COMPLETED", "message": null}