{"trial_id": "0024", "hyperparameters": {"space": [{"class_name": "Int", "config": {"name": "units", "default": null, "conditions": [], "min_value": 10, "max_value": 512, "step": 32, "sampling": "linear"}}, {"class_name": "Float", "config": {"name": "learning_rate", "default": 0.0001, "conditions": [], "min_value": 0.0001, "max_value": 0.01, "step": null, "sampling": "log"}}], "values": {"units": 74, "learning_rate": 0.00985793043338185, "tuner/epochs": 10, "tuner/initial_epoch": 4, "tuner/bracket": 1, "tuner/round": 1, "tuner/trial_id": "0018"}}, "metrics": {"metrics": {"loss": {"direction": "min", "observations": [{"value": [0.5871826410293579], "step": 4}]}, "accuracy": {"direction": "max", "observations": [{"value": [0.8365741968154907], "step": 4}]}, "val_loss": {"direction": "min", "observations": [{"value": [0.5432184338569641], "step": 4}]}, "val_accuracy": {"direction": "max", "observations": [{"value": [0.8393367528915405], "step": 4}]}}}, "score": 0.8393367528915405, "best_step": 4, "status": "COMPLETED", "message": null}